request_mapper/__init__.py
request_mapper/integration/__init__.py
request_mapper/integration/flask_integration.py
request_mapper/integration/integration.py
request_mapper/py.typed
request_mapper/types.py
request_mapper-0.1.0.dist-info/METADATA
request_mapper-0.1.0.dist-info/WHEEL
request_mapper-0.1.0.dist-info/RECORD
